Lab93_TradeClient/AccountData.py
Lab93_TradeClient/MarketData.py
Lab93_TradeClient/__init__.py
Lab93_TradeClient-0.0.3.dist-info/METADATA
Lab93_TradeClient-0.0.3.dist-info/WHEEL
Lab93_TradeClient-0.0.3.dist-info/top_level.txt
Lab93_TradeClient-0.0.3.dist-info/RECORD
