Metadata-Version: 2.1
Name: Lab93-TradeClient
Version: 0.0.3
Summary: Manage Lab funding through risk management.
Author-email: Hunter Dale <guyyatsu@gmail.com>
Project-URL: Homepage, https://github.com/guyyatsu/Lab93-TradeClient
Project-URL: Bug Tracker, https://github.com/guyyatsu/Lab93-TradeClient/issues
Classifier: Programming Language :: Python :: 3
Classifier: License :: OSI Approved :: MIT License
Classifier: Operating System :: OS Independent
Requires-Python: >=3.7
Requires-Dist: Lab93-Cryptogram
Requires-Dist: alpaca-py
